functionaltools/__init__.py
tests/__init__.py
tests/test_functionaltools.py
functionaltools-0.0.2.dist-info/METADATA
functionaltools-0.0.2.dist-info/WHEEL
functionaltools-0.0.2.dist-info/top_level.txt
functionaltools-0.0.2.dist-info/RECORD
