Metadata-Version: 2.1
Name: functionaltools
Version: 0.0.2
Summary: Python functions to facilitate functional programming.
Home-page: https://github.com/lewisrodgers/pyfunctionaltools
Author: Lewis Rodgers
Author-email: contact@lewisrodgers.com
License: UNKNOWN
Platform: UNKNOWN
